ShieldCipher/__init__.py
ShieldCipher/bin/__init__.py
ShieldCipher/bin/cli.py
ShieldCipher/encryption/__init__.py
ShieldCipher/encryption/symmetric.py
ShieldCipher-1.2.1.dist-info/LICENSE
ShieldCipher-1.2.1.dist-info/METADATA
ShieldCipher-1.2.1.dist-info/WHEEL
ShieldCipher-1.2.1.dist-info/entry_points.txt
ShieldCipher-1.2.1.dist-info/top_level.txt
ShieldCipher-1.2.1.dist-info/RECORD
