Metadata-Version: 2.1
Name: ShieldCipher
Version: 1.2.1
Summary: Python library for cybersecurity
Home-page: https://rah-code-dev.github.io/ShieldCipher
Author: RAH Code
Author-email: contacto@rahcode.com
License: MIT License
License-File: LICENSE
Requires-Dist: pycryptodome >=3.19.1
